shared_architecture/__init__.py
shared_architecture/connection_manager.py
shared_architecture/enums.py
shared_architecture/exceptions.py
shared_architecture/run_all_tests.py
shared_architecture/config/__init__.py
shared_architecture/config/config_loader.py
shared_architecture/config/global_settings.py
shared_architecture/config/secrets_manager.py
shared_architecture/config/validators.py
shared_architecture/connections/__init__.py
shared_architecture/connections/connection_manager.py
shared_architecture/connections/mongodb_client.py
shared_architecture/connections/rabbitmq_client.py
shared_architecture/connections/redis_client.py
shared_architecture/connections/timescaledb_client.py
shared_architecture/db/__init__.py
shared_architecture/db/base.py
shared_architecture/db/connections.py
shared_architecture/db/migrations.py
shared_architecture/db/repository.py
shared_architecture/db/session.py
shared_architecture/db/timescaledb_bulk_utils.py
shared_architecture/db/models/__init__.py
shared_architecture/db/models/activity_log.py
shared_architecture/db/models/broker.py
shared_architecture/db/models/database.py
shared_architecture/db/models/enums.py
shared_architecture/db/models/group.py
shared_architecture/db/models/historical_data.py
shared_architecture/db/models/holding_model.py
shared_architecture/db/models/margin_model.py
shared_architecture/db/models/order_model.py
shared_architecture/db/models/position_model.py
shared_architecture/db/models/symbol.py
shared_architecture/db/models/symbol_update.py
shared_architecture/db/models/tick_data.py
shared_architecture/db/models/trading_account.py
shared_architecture/db/models/user.py
shared_architecture/mocks/__init__.py
shared_architecture/mocks/mongodb_client.py
shared_architecture/mocks/rabbitmq_client.py
shared_architecture/mocks/redis_client.py
shared_architecture/mocks/timescaledb_client.py
shared_architecture/schemas/__init__.py
shared_architecture/schemas/feed.py
shared_architecture/schemas/group.py
shared_architecture-0.5.0.dist-info/METADATA
shared_architecture-0.5.0.dist-info/WHEEL
shared_architecture-0.5.0.dist-info/top_level.txt
shared_architecture-0.5.0.dist-info/RECORD
