Metadata-Version: 2.1
Name: shared-architecture
Version: 0.5.0
Summary: A shared Python library for backend microservices, including models, utilities, and configurations.
Home-page: https://github.com/raghurammutya/shared_architecture
Author: Raghuram Mutya
Author-email: raghu.mutya@gmail.com
Keywords: shared library microservices architecture configuration utilities
Classifier: Programming Language :: Python :: 3
Classifier: Programming Language :: Python :: 3.8
Classifier: Operating System :: OS Independent
Classifier: License :: OSI Approved :: MIT License
Requires-Python: >=3.8
Requires-Dist: SQLAlchemy>=1.4
Requires-Dist: psycopg2-binary>=2.9
Requires-Dist: redis>=4.0
Requires-Dist: pika>=1.3
Requires-Dist: requests>=2.25
Requires-Dist: pytest>=7.0
Requires-Dist: pydantic>=1.10
Requires-Dist: circuitbreaker>=1.3
